app/__init__.py
app/__main__.py
app/cli.py
app/commands.py
app/configfile.py
move_my_files-0.2.4.dist-info/LICENSE
move_my_files-0.2.4.dist-info/METADATA
move_my_files-0.2.4.dist-info/WHEEL
move_my_files-0.2.4.dist-info/entry_points.txt
move_my_files-0.2.4.dist-info/top_level.txt
move_my_files-0.2.4.dist-info/RECORD
