Metadata-Version: 2.1
Name: move-my-files
Version: 0.2.4
Summary: CLI tools to organize files on your computer
Home-page: https://github.com/jan25/move-my-files
Author: Abhilash Gnan
Author-email: abhilashgnan@gmail.com
License: UNKNOWN
Platform: UNKNOWN
Classifier: Development Status :: 4 - Beta
Classifier: License :: OSI Approved :: MIT License
Classifier: Programming Language :: Python :: 3.5
Classifier: Programming Language :: Python :: 3.6
Classifier: Programming Language :: Python :: 3.7
Classifier: Programming Language :: Python :: 3.8
Classifier: Programming Language :: Python :: 3 :: Only
Requires-Python: >=3.5, <4
Requires-Dist: watchdog
Requires-Dist: Click
Requires-Dist: pyyaml
Provides-Extra: dev
Requires-Dist: pytest ; extra == 'dev'
